dwd_pollen_api/__init__.py
dwd_pollen_api/client.py
dwd_pollen_api_client-0.1.3.dist-info/licenses/LICENSE
dwd_pollen_api_client-0.1.3.dist-info/METADATA
dwd_pollen_api_client-0.1.3.dist-info/WHEEL
dwd_pollen_api_client-0.1.3.dist-info/top_level.txt
dwd_pollen_api_client-0.1.3.dist-info/RECORD
