Metadata-Version: 2.4
Name: dwd-pollen-api_client
Version: 0.1.3
Summary: Async client for the DWD pollen forecast data API
Author-email: Sven Gerlach <pypi@rexkramer.de>
License: MIT License
Project-URL: Homepage, https://github.com/rexdek/dwd_pollen_api_client
Project-URL: Repository, https://github.com/rexdek/dwd_pollen_api_client
Requires-Python: >=3.9
License-File: LICENSE
Requires-Dist: aiohttp
Dynamic: license-file
